README.md
setup.cfg
setup.py
src/dbod_entities_malformed.py
src/dbod_helpers.py
src/dbod_innodb_cluster_ping.py
src/dbod_instances.py
src/dbod_ping.py
src/dbod_plugin.py
src/dbod_replication.py
src/dbod_slave.py
src/collectd_dbod.egg-info/PKG-INFO
src/collectd_dbod.egg-info/SOURCES.txt
src/collectd_dbod.egg-info/dependency_links.txt
src/collectd_dbod.egg-info/requires.txt
src/collectd_dbod.egg-info/top_level.txt
test/test_dbod_collectd_helpers.py
test/test_dbod_collectd_plugin.py
test/test_dbod_collectd_plugin_entities_malformed.py
test/test_dbod_collectd_plugin_ping.py
test/test_dbod_instances.py
test/test_dbod_slave.py